samsara_fn/__init__.py
samsara_fn/clilogger.py
samsara_fn/helptext.py
samsara_fn/main.py
samsara_fn/artifacts/bundle/ignore.txt
samsara_fn/artifacts/dependencies/v6.txt
samsara_fn/artifacts/dependencies/v7.txt
samsara_fn/artifacts/dependencies/v8.txt
samsara_fn/artifacts/schemas/alertPayload.json
samsara_fn/artifacts/templates/ignore.txt
samsara_fn/artifacts/templates/access-bundle-content/function.py
samsara_fn/artifacts/templates/access-bundle-content/samsarafnbundle.py
samsara_fn/artifacts/templates/additional-python-dependencies/function.py
samsara_fn/artifacts/templates/additional-python-dependencies/samsarafndeps.py
samsara_fn/artifacts/templates/additional-python-dependencies/run-before-bundle/README.md
samsara_fn/artifacts/templates/additional-python-dependencies/run-before-bundle/install_deps_to_lib.py
samsara_fn/artifacts/templates/additional-python-dependencies/run-before-bundle/requirements.txt
samsara_fn/artifacts/templates/correlation-logging/function.py
samsara_fn/artifacts/templates/correlation-logging/samsarafnlogs.py
samsara_fn/artifacts/templates/just-secrets/function.py
samsara_fn/artifacts/templates/just-secrets/samsarafnsecrets.py
samsara_fn/artifacts/templates/persistent-storage/function.py
samsara_fn/artifacts/templates/persistent-storage/samsarafnstorage.py
samsara_fn/artifacts/templates/resolve-samsara-region/function.py
samsara_fn/artifacts/templates/resolve-samsara-region/samsarafnregion.py
samsara_fn/artifacts/templates/temporary-runtime-storage/README.md
samsara_fn/artifacts/templates/temporary-runtime-storage/function.py
samsara_fn/artifacts/templates/temporary-runtime-storage/samsarafntempstorage.py
samsara_fn/commands/__init__.py
samsara_fn/commands/bundle.py
samsara_fn/commands/completion.py
samsara_fn/commands/dependencies.py
samsara_fn/commands/init.py
samsara_fn/commands/run.py
samsara_fn/commands/schemas.py
samsara_fn/commands/templates.py
samsara_fn/commands/utils.py
samsara_fn/commands/validate.py
samsara_fn-0.16.0.dist-info/METADATA
samsara_fn-0.16.0.dist-info/WHEEL
samsara_fn-0.16.0.dist-info/entry_points.txt
samsara_fn-0.16.0.dist-info/top_level.txt
samsara_fn-0.16.0.dist-info/RECORD
