Metadata-Version: 2.4
Name: samsara-fn
Version: 0.16.0
Summary: A CLI tool for Samsara Functions
Requires-Python: >=3.12
Requires-Dist: boto3>=1.26.0
Provides-Extra: shell-completion
Requires-Dist: argcomplete>=3.6.2; extra == "shell-completion"
